wove/__init__.py
wove/api.py
wove/background.py
wove/context.py
wove/debug.py
wove/errors.py
wove/executor.py
wove/graph.py
wove/helpers.py
wove/result.py
wove/task.py
wove/vars.py
wove/weave.py
wove-1.0.0.dist-info/licenses/LICENSE
wove-1.0.0.dist-info/METADATA
wove-1.0.0.dist-info/WHEEL
wove-1.0.0.dist-info/top_level.txt
wove-1.0.0.dist-info/RECORD
