Metadata-Version: 2.4
Name: wove
Version: 1.0.0
Summary: Beautiful python async orchestration
Author: curvedinf
License: MIT License
Project-URL: Homepage, https://github.com/curvedinf/wove
Project-URL: Bug Tracker, https://github.com/curvedinf/wove/issues
Classifier: Programming Language :: Python :: 3
Classifier: License :: OSI Approved :: MIT License
Classifier: Operating System :: OS Independent
Classifier: Intended Audience :: Developers
Classifier: Topic :: Software Development :: Libraries :: Python Modules
Requires-Python: >=3.8
License-File: LICENSE
Requires-Dist: cloudpickle
Provides-Extra: dev
Requires-Dist: pytest-asyncio; extra == "dev"
Requires-Dist: ruff; extra == "dev"
Requires-Dist: pytest-cov; extra == "dev"
Provides-Extra: examples
Requires-Dist: httpx; extra == "examples"
Requires-Dist: numpy; extra == "examples"
Requires-Dist: requests; extra == "examples"
Dynamic: license-file
